funtask/__about__.py
funtask/__init__.py
funtask/fun_task_manager.py
funtask/utils.py
funtask/local/__init__.py
funtask/local/local_fun_task_manager.py
funtask-0.0.4.dist-info/METADATA
funtask-0.0.4.dist-info/WHEEL
funtask-0.0.4.dist-info/licenses/LICENSE.txt
funtask-0.0.4.dist-info/RECORD
