Metadata-Version: 2.1
Name: funtask
Version: 0.0.4
Summary: A Python framework for stateful functional task dispatching and execution
Project-URL: Documentation, https://github.com/zqqqqz2000/funtask#readme
Project-URL: Issues, https://github.com/zqqqqz2000/funtask/issues
Project-URL: Source, https://github.com/zqqqqz2000/funtask
Author-email: zqqqqz2000 <zqqqqz2000@sina.cn>
License-File: LICENSE.txt
Classifier: Development Status :: 4 - Beta
Classifier: Programming Language :: Python
Classifier: Programming Language :: Python :: 3.7
Classifier: Programming Language :: Python :: 3.8
Classifier: Programming Language :: Python :: 3.9
Classifier: Programming Language :: Python :: 3.10
Classifier: Programming Language :: Python :: 3.11
Classifier: Programming Language :: Python :: Implementation :: CPython
Classifier: Programming Language :: Python :: Implementation :: PyPy
Requires-Python: >=3.7
Requires-Dist: dill
Requires-Dist: mypy-extensions
